pdf34/__init__.py
pdf34/pdf2image.py
pdf34/pdf2text.py
pdf34-1.0.0.dist-info/LICENCE
pdf34-1.0.0.dist-info/METADATA
pdf34-1.0.0.dist-info/WHEEL
pdf34-1.0.0.dist-info/top_level.txt
pdf34-1.0.0.dist-info/RECORD
